{
    "structures":            ["RSS_HEA/conf_*"],
    "interaction": {
            "type":           "deepmd",
            "model":          "frozen_model.pb",
            "type_map":       {"Co": 0, "Cr": 1, "Fe": 2, "Mn": 3, "Ni": 4}
        },
    "relaxation": {
            "cal_setting":   {"etol":       0,
                              "ftol":     1e-10,
                              "maxiter":   5000,
                              "maximal":  500000}
        },
    "properties": [
        {
         "type":         "eos",
         "vol_start":    0.6,
         "vol_end":      1.4,
         "vol_step":     0.05,
          "cal_setting":  {"etol": 0,
                         "ftol": 1e-10}
        },
        {
         "type":         "elastic",
         "norm_deform":  1e-2,
         "shear_deform": 1e-2,
         "cal_setting":  {"etol": 0,
                         "ftol": 1e-10}
        }
        ]
}
